hubmap_api_py_client/__init__.py
hubmap_api_py_client/errors.py
hubmap_api_py_client/external.py
hubmap_api_py_client/internal.py
hubmap_api_py_client-0.0.11.dist-info/LICENSE
hubmap_api_py_client-0.0.11.dist-info/METADATA
hubmap_api_py_client-0.0.11.dist-info/WHEEL
hubmap_api_py_client-0.0.11.dist-info/top_level.txt
hubmap_api_py_client-0.0.11.dist-info/RECORD
