Metadata-Version: 2.1
Name: hubmap-api-py-client
Version: 0.0.11
Summary: Client for the HuBMAP Cells API
Home-page: https://github.com/hubmapconsortium/hubmap-api-py-client
Author: Chuck McCallum
Author-email: mccallucc+cells_client@gmail.com
Classifier: Programming Language :: Python :: 3
Classifier: License :: OSI Approved :: MIT License
Classifier: Operating System :: OS Independent
Requires-Python: >=3.8
License-File: LICENSE
Requires-Dist: requests (>=2.0.0)
